elves/__init__.py
elves/errors.py
elves/execute.py
pyelves-0.0.3.dist-info/METADATA
pyelves-0.0.3.dist-info/WHEEL
pyelves-0.0.3.dist-info/top_level.txt
pyelves-0.0.3.dist-info/RECORD
