Metadata-Version: 2.1
Name: pyelves
Version: 0.0.3
Summary: A package designed to make Python programming easier.
Home-page: UNKNOWN
Author: Alex Pylypenko
Author-email: macaquedev@gmail.com
License: MIT
Platform: UNKNOWN
Classifier: Programming Language :: Python :: 3
Classifier: License :: OSI Approved :: MIT License
Classifier: Operating System :: OS Independent
Requires-Python: >=3.6
